MANIFEST.in
setup.py
./__init__.py
./__openerp__.py
./controllers/__init__.py
./controllers/main.py
i18n/ar.po
i18n/bg.po
i18n/bn.po
i18n/bs.po
i18n/ca.po
i18n/cs.po
i18n/da.po
i18n/de.po
i18n/en_AU.po
i18n/en_GB.po
i18n/es.po
i18n/es_CL.po
i18n/es_CR.po
i18n/es_DO.po
i18n/es_EC.po
i18n/es_MX.po
i18n/es_PE.po
i18n/et.po
i18n/fa.po
i18n/fi.po
i18n/fr.po
i18n/gl.po
i18n/gu.po
i18n/hr.po
i18n/hu.po
i18n/id.po
i18n/it.po
i18n/ja.po
i18n/ka.po
i18n/ko.po
i18n/lt.po
i18n/mk.po
i18n/mn.po
i18n/nb.po
i18n/nl.po
i18n/nl_BE.po
i18n/pl.po
i18n/pt.po
i18n/pt_BR.po
i18n/ro.po
i18n/ru.po
i18n/sl.po
i18n/sq.po
i18n/sr@latin.po
i18n/sv.po
i18n/th.po
i18n/tr.po
i18n/web_diagram.pot
i18n/zh_CN.po
i18n/zh_TW.po
openerp_web_diagram.egg-info/PKG-INFO
openerp_web_diagram.egg-info/SOURCES.txt
openerp_web_diagram.egg-info/dependency_links.txt
openerp_web_diagram.egg-info/requires.txt
openerp_web_diagram.egg-info/top_level.txt
static/lib/js/Curry-1.0.1.js
static/lib/js/jquery.mousewheel.js
static/lib/js/raphael.js
static/lib/js/seedrandom.js
static/src/js/diagram.js
static/src/js/graph.js
static/src/js/vec2.js
static/src/xml/base_diagram.xml